[
  {
    "test_case": "EXIST2024",
    "id": "110001",
    "value": "YES"
  },
  {
    "test_case": "EXIST2024",
    "id": "110003",
    "value": "YES"
  },
  {
    "test_case": "EXIST2024",
    "id": "110005",
    "value": "YES"
  },
  {
    "test_case": "EXIST2024",
    "id": "110008",
    "value": "YES"
  },
  {
    "test_case": "EXIST2024",
    "id": "110012",
    "value": "YES"
  },
  {
    "test_case": "EXIST2024",
    "id": "110015",
    "value": "YES"
  },
  {
    "test_case": "EXIST2024",
    "id": "110016",
    "value": "YES"
  },
  {
    "test_case": "EXIST2024",
    "id": "110018",
    "value": "YES"
  },
  {
    "test_case": "EXIST2024",
    "id": "110022",
    "value": "YES"
  },
  {
    "test_case": "EXIST2024",
    "id": "110026",
    "value": "YES"
  },
  {
    "test_case": "EXIST2024",
    "id": "110027",
    "value": "YES"
  },
  {
    "test_case": "EXIST2024",
    "id": "110034",
    "value": "YES"
  },
  {
    "test_case": "EXIST2024",
    "id": "110037",
    "value": "YES"
  },
  {
    "test_case": "EXIST2024",
    "id": "110041",
    "value": "YES"
  },
  {
    "test_case": "EXIST2024",
    "id": "110061",
    "value": "YES"
  },
  {
    "test_case": "EXIST2024",
    "id": "110063",
    "value": "YES"
  },
  {
    "test_case": "EXIST2024",
    "id": "110065",
    "value": "YES"
  },
  {
    "test_case": "EXIST2024",
    "id": "110066",
    "value": "NO"
  },
  {
    "test_case": "EXIST2024",
    "id": "110068",
    "value": "YES"
  },
  {
    "test_case": "EXIST2024",
    "id": "110069",
    "value": "YES"
  },
  {
    "test_case": "EXIST2024",
    "id": "110076",
    "value": "YES"
  },
  {
    "test_case": "EXIST2024",
    "id": "110083",
    "value": "YES"
  },
  {
    "test_case": "EXIST2024",
    "id": "110089",
    "value": "YES"
  },
  {
    "test_case": "EXIST2024",
    "id": "110090",
    "value": "YES"
  },
  {
    "test_case": "EXIST2024",
    "id": "110101",
    "value": "YES"
  },
  {
    "test_case": "EXIST2024",
    "id": "110104",
    "value": "YES"
  },
  {
    "test_case": "EXIST2024",
    "id": "110106",
    "value": "YES"
  },
  {
    "test_case": "EXIST2024",
    "id": "110111",
    "value": "YES"
  },
  {
    "test_case": "EXIST2024",
    "id": "110113",
    "value": "YES"
  },
  {
    "test_case": "EXIST2024",
    "id": "110114",
    "value": "YES"
  },
  {
    "test_case": "EXIST2024",
    "id": "110116",
    "value": "YES"
  },
  {
    "test_case": "EXIST2024",
    "id": "110118",
    "value": "YES"
  },
  {
    "test_case": "EXIST2024",
    "id": "110123",
    "value": "YES"
  },
  {
    "test_case": "EXIST2024",
    "id": "110126",
    "value": "YES"
  },
  {
    "test_case": "EXIST2024",
    "id": "110130",
    "value": "YES"
  },
  {
    "test_case": "EXIST2024",
    "id": "110133",
    "value": "NO"
  },
  {
    "test_case": "EXIST2024",
    "id": "110136",
    "value": "YES"
  },
  {
    "test_case": "EXIST2024",
    "id": "110139",
    "value": "YES"
  },
  {
    "test_case": "EXIST2024",
    "id": "110140",
    "value": "YES"
  },
  {
    "test_case": "EXIST2024",
    "id": "110147",
    "value": "YES"
  },
  {
    "test_case": "EXIST2024",
    "id": "110156",
    "value": "YES"
  },
  {
    "test_case": "EXIST2024",
    "id": "110166",
    "value": "YES"
  },
  {
    "test_case": "EXIST2024",
    "id": "110172",
    "value": "YES"
  },
  {
    "test_case": "EXIST2024",
    "id": "110173",
    "value": "YES"
  },
  {
    "test_case": "EXIST2024",
    "id": "110183",
    "value": "YES"
  },
  {
    "test_case": "EXIST2024",
    "id": "110185",
    "value": "NO"
  },
  {
    "test_case": "EXIST2024",
    "id": "110187",
    "value": "YES"
  },
  {
    "test_case": "EXIST2024",
    "id": "110188",
    "value": "YES"
  },
  {
    "test_case": "EXIST2024",
    "id": "110190",
    "value": "YES"
  },
  {
    "test_case": "EXIST2024",
    "id": "110191",
    "value": "YES"
  },
  {
    "test_case": "EXIST2024",
    "id": "110195",
    "value": "YES"
  },
  {
    "test_case": "EXIST2024",
    "id": "110197",
    "value": "YES"
  },
  {
    "test_case": "EXIST2024",
    "id": "110202",
    "value": "YES"
  },
  {
    "test_case": "EXIST2024",
    "id": "110206",
    "value": "YES"
  },
  {
    "test_case": "EXIST2024",
    "id": "110208",
    "value": "YES"
  },
  {
    "test_case": "EXIST2024",
    "id": "110217",
    "value": "YES"
  },
  {
    "test_case": "EXIST2024",
    "id": "110222",
    "value": "YES"
  },
  {
    "test_case": "EXIST2024",
    "id": "110225",
    "value": "NO"
  },
  {
    "test_case": "EXIST2024",
    "id": "110239",
    "value": "YES"
  },
  {
    "test_case": "EXIST2024",
    "id": "110246",
    "value": "YES"
  },
  {
    "test_case": "EXIST2024",
    "id": "110247",
    "value": "YES"
  },
  {
    "test_case": "EXIST2024",
    "id": "110248",
    "value": "YES"
  },
  {
    "test_case": "EXIST2024",
    "id": "110259",
    "value": "YES"
  },
  {
    "test_case": "EXIST2024",
    "id": "110261",
    "value": "YES"
  },
  {
    "test_case": "EXIST2024",
    "id": "110263",
    "value": "YES"
  },
  {
    "test_case": "EXIST2024",
    "id": "110267",
    "value": "YES"
  },
  {
    "test_case": "EXIST2024",
    "id": "110272",
    "value": "YES"
  },
  {
    "test_case": "EXIST2024",
    "id": "110282",
    "value": "NO"
  },
  {
    "test_case": "EXIST2024",
    "id": "110293",
    "value": "YES"
  },
  {
    "test_case": "EXIST2024",
    "id": "110294",
    "value": "YES"
  },
  {
    "test_case": "EXIST2024",
    "id": "110295",
    "value": "YES"
  },
  {
    "test_case": "EXIST2024",
    "id": "110297",
    "value": "YES"
  },
  {
    "test_case": "EXIST2024",
    "id": "110300",
    "value": "NO"
  },
  {
    "test_case": "EXIST2024",
    "id": "110312",
    "value": "YES"
  },
  {
    "test_case": "EXIST2024",
    "id": "110337",
    "value": "YES"
  },
  {
    "test_case": "EXIST2024",
    "id": "110338",
    "value": "YES"
  },
  {
    "test_case": "EXIST2024",
    "id": "110341",
    "value": "YES"
  },
  {
    "test_case": "EXIST2024",
    "id": "110344",
    "value": "YES"
  },
  {
    "test_case": "EXIST2024",
    "id": "110347",
    "value": "YES"
  },
  {
    "test_case": "EXIST2024",
    "id": "110352",
    "value": "YES"
  },
  {
    "test_case": "EXIST2024",
    "id": "110353",
    "value": "NO"
  },
  {
    "test_case": "EXIST2024",
    "id": "110354",
    "value": "YES"
  },
  {
    "test_case": "EXIST2024",
    "id": "110364",
    "value": "YES"
  },
  {
    "test_case": "EXIST2024",
    "id": "110376",
    "value": "YES"
  },
  {
    "test_case": "EXIST2024",
    "id": "110383",
    "value": "YES"
  },
  {
    "test_case": "EXIST2024",
    "id": "110402",
    "value": "NO"
  },
  {
    "test_case": "EXIST2024",
    "id": "110406",
    "value": "YES"
  },
  {
    "test_case": "EXIST2024",
    "id": "110409",
    "value": "YES"
  },
  {
    "test_case": "EXIST2024",
    "id": "110413",
    "value": "YES"
  },
  {
    "test_case": "EXIST2024",
    "id": "110416",
    "value": "YES"
  },
  {
    "test_case": "EXIST2024",
    "id": "110418",
    "value": "YES"
  },
  {
    "test_case": "EXIST2024",
    "id": "110424",
    "value": "YES"
  },
  {
    "test_case": "EXIST2024",
    "id": "110427",
    "value": "YES"
  },
  {
    "test_case": "EXIST2024",
    "id": "110432",
    "value": "YES"
  },
  {
    "test_case": "EXIST2024",
    "id": "110436",
    "value": "YES"
  },
  {
    "test_case": "EXIST2024",
    "id": "110438",
    "value": "YES"
  },
  {
    "test_case": "EXIST2024",
    "id": "110439",
    "value": "YES"
  },
  {
    "test_case": "EXIST2024",
    "id": "110442",
    "value": "YES"
  },
  {
    "test_case": "EXIST2024",
    "id": "110444",
    "value": "YES"
  },
  {
    "test_case": "EXIST2024",
    "id": "110455",
    "value": "YES"
  },
  {
    "test_case": "EXIST2024",
    "id": "110460",
    "value": "NO"
  },
  {
    "test_case": "EXIST2024",
    "id": "110461",
    "value": "YES"
  },
  {
    "test_case": "EXIST2024",
    "id": "110462",
    "value": "YES"
  },
  {
    "test_case": "EXIST2024",
    "id": "110463",
    "value": "NO"
  },
  {
    "test_case": "EXIST2024",
    "id": "110464",
    "value": "YES"
  },
  {
    "test_case": "EXIST2024",
    "id": "110467",
    "value": "YES"
  },
  {
    "test_case": "EXIST2024",
    "id": "110470",
    "value": "YES"
  },
  {
    "test_case": "EXIST2024",
    "id": "110478",
    "value": "YES"
  },
  {
    "test_case": "EXIST2024",
    "id": "110489",
    "value": "YES"
  },
  {
    "test_case": "EXIST2024",
    "id": "110503",
    "value": "YES"
  },
  {
    "test_case": "EXIST2024",
    "id": "110504",
    "value": "YES"
  },
  {
    "test_case": "EXIST2024",
    "id": "110509",
    "value": "YES"
  },
  {
    "test_case": "EXIST2024",
    "id": "110512",
    "value": "YES"
  },
  {
    "test_case": "EXIST2024",
    "id": "110514",
    "value": "YES"
  },
  {
    "test_case": "EXIST2024",
    "id": "110515",
    "value": "NO"
  },
  {
    "test_case": "EXIST2024",
    "id": "110519",
    "value": "YES"
  },
  {
    "test_case": "EXIST2024",
    "id": "110526",
    "value": "YES"
  },
  {
    "test_case": "EXIST2024",
    "id": "110530",
    "value": "YES"
  },
  {
    "test_case": "EXIST2024",
    "id": "110531",
    "value": "YES"
  },
  {
    "test_case": "EXIST2024",
    "id": "110532",
    "value": "NO"
  },
  {
    "test_case": "EXIST2024",
    "id": "110535",
    "value": "YES"
  },
  {
    "test_case": "EXIST2024",
    "id": "110540",
    "value": "YES"
  },
  {
    "test_case": "EXIST2024",
    "id": "110543",
    "value": "YES"
  },
  {
    "test_case": "EXIST2024",
    "id": "110554",
    "value": "YES"
  },
  {
    "test_case": "EXIST2024",
    "id": "110559",
    "value": "YES"
  },
  {
    "test_case": "EXIST2024",
    "id": "110564",
    "value": "YES"
  },
  {
    "test_case": "EXIST2024",
    "id": "110578",
    "value": "YES"
  },
  {
    "test_case": "EXIST2024",
    "id": "110579",
    "value": "YES"
  },
  {
    "test_case": "EXIST2024",
    "id": "110588",
    "value": "YES"
  },
  {
    "test_case": "EXIST2024",
    "id": "110590",
    "value": "YES"
  },
  {
    "test_case": "EXIST2024",
    "id": "110602",
    "value": "YES"
  },
  {
    "test_case": "EXIST2024",
    "id": "110604",
    "value": "YES"
  },
  {
    "test_case": "EXIST2024",
    "id": "110605",
    "value": "YES"
  },
  {
    "test_case": "EXIST2024",
    "id": "110613",
    "value": "YES"
  },
  {
    "test_case": "EXIST2024",
    "id": "110619",
    "value": "YES"
  },
  {
    "test_case": "EXIST2024",
    "id": "110623",
    "value": "YES"
  },
  {
    "test_case": "EXIST2024",
    "id": "110624",
    "value": "YES"
  },
  {
    "test_case": "EXIST2024",
    "id": "110634",
    "value": "YES"
  },
  {
    "test_case": "EXIST2024",
    "id": "110643",
    "value": "YES"
  },
  {
    "test_case": "EXIST2024",
    "id": "110649",
    "value": "YES"
  },
  {
    "test_case": "EXIST2024",
    "id": "110651",
    "value": "YES"
  },
  {
    "test_case": "EXIST2024",
    "id": "110659",
    "value": "NO"
  },
  {
    "test_case": "EXIST2024",
    "id": "110669",
    "value": "YES"
  },
  {
    "test_case": "EXIST2024",
    "id": "110675",
    "value": "YES"
  },
  {
    "test_case": "EXIST2024",
    "id": "110679",
    "value": "YES"
  },
  {
    "test_case": "EXIST2024",
    "id": "110680",
    "value": "YES"
  },
  {
    "test_case": "EXIST2024",
    "id": "110686",
    "value": "YES"
  },
  {
    "test_case": "EXIST2024",
    "id": "110694",
    "value": "YES"
  },
  {
    "test_case": "EXIST2024",
    "id": "110695",
    "value": "YES"
  },
  {
    "test_case": "EXIST2024",
    "id": "110702",
    "value": "YES"
  },
  {
    "test_case": "EXIST2024",
    "id": "110715",
    "value": "YES"
  },
  {
    "test_case": "EXIST2024",
    "id": "110720",
    "value": "YES"
  },
  {
    "test_case": "EXIST2024",
    "id": "110726",
    "value": "YES"
  },
  {
    "test_case": "EXIST2024",
    "id": "110731",
    "value": "YES"
  },
  {
    "test_case": "EXIST2024",
    "id": "110735",
    "value": "YES"
  },
  {
    "test_case": "EXIST2024",
    "id": "110736",
    "value": "YES"
  },
  {
    "test_case": "EXIST2024",
    "id": "110742",
    "value": "YES"
  },
  {
    "test_case": "EXIST2024",
    "id": "110751",
    "value": "YES"
  },
  {
    "test_case": "EXIST2024",
    "id": "110755",
    "value": "YES"
  },
  {
    "test_case": "EXIST2024",
    "id": "110756",
    "value": "YES"
  },
  {
    "test_case": "EXIST2024",
    "id": "110759",
    "value": "YES"
  },
  {
    "test_case": "EXIST2024",
    "id": "110779",
    "value": "YES"
  },
  {
    "test_case": "EXIST2024",
    "id": "110789",
    "value": "YES"
  },
  {
    "test_case": "EXIST2024",
    "id": "110792",
    "value": "YES"
  },
  {
    "test_case": "EXIST2024",
    "id": "110797",
    "value": "YES"
  },
  {
    "test_case": "EXIST2024",
    "id": "110804",
    "value": "YES"
  },
  {
    "test_case": "EXIST2024",
    "id": "110808",
    "value": "YES"
  },
  {
    "test_case": "EXIST2024",
    "id": "110816",
    "value": "YES"
  },
  {
    "test_case": "EXIST2024",
    "id": "110823",
    "value": "YES"
  },
  {
    "test_case": "EXIST2024",
    "id": "110826",
    "value": "NO"
  },
  {
    "test_case": "EXIST2024",
    "id": "110831",
    "value": "YES"
  },
  {
    "test_case": "EXIST2024",
    "id": "110838",
    "value": "YES"
  },
  {
    "test_case": "EXIST2024",
    "id": "110850",
    "value": "YES"
  },
  {
    "test_case": "EXIST2024",
    "id": "110852",
    "value": "YES"
  },
  {
    "test_case": "EXIST2024",
    "id": "110853",
    "value": "YES"
  },
  {
    "test_case": "EXIST2024",
    "id": "110860",
    "value": "YES"
  },
  {
    "test_case": "EXIST2024",
    "id": "110864",
    "value": "YES"
  },
  {
    "test_case": "EXIST2024",
    "id": "110865",
    "value": "YES"
  },
  {
    "test_case": "EXIST2024",
    "id": "110872",
    "value": "YES"
  },
  {
    "test_case": "EXIST2024",
    "id": "110878",
    "value": "YES"
  },
  {
    "test_case": "EXIST2024",
    "id": "110879",
    "value": "YES"
  },
  {
    "test_case": "EXIST2024",
    "id": "110884",
    "value": "YES"
  },
  {
    "test_case": "EXIST2024",
    "id": "110886",
    "value": "YES"
  },
  {
    "test_case": "EXIST2024",
    "id": "110887",
    "value": "YES"
  },
  {
    "test_case": "EXIST2024",
    "id": "110888",
    "value": "YES"
  },
  {
    "test_case": "EXIST2024",
    "id": "110891",
    "value": "YES"
  },
  {
    "test_case": "EXIST2024",
    "id": "110893",
    "value": "YES"
  },
  {
    "test_case": "EXIST2024",
    "id": "110902",
    "value": "YES"
  },
  {
    "test_case": "EXIST2024",
    "id": "110903",
    "value": "YES"
  },
  {
    "test_case": "EXIST2024",
    "id": "110905",
    "value": "YES"
  },
  {
    "test_case": "EXIST2024",
    "id": "110909",
    "value": "YES"
  },
  {
    "test_case": "EXIST2024",
    "id": "110913",
    "value": "YES"
  },
  {
    "test_case": "EXIST2024",
    "id": "110917",
    "value": "YES"
  },
  {
    "test_case": "EXIST2024",
    "id": "110927",
    "value": "YES"
  },
  {
    "test_case": "EXIST2024",
    "id": "110930",
    "value": "YES"
  },
  {
    "test_case": "EXIST2024",
    "id": "110938",
    "value": "YES"
  },
  {
    "test_case": "EXIST2024",
    "id": "110944",
    "value": "YES"
  },
  {
    "test_case": "EXIST2024",
    "id": "110950",
    "value": "YES"
  },
  {
    "test_case": "EXIST2024",
    "id": "110951",
    "value": "YES"
  },
  {
    "test_case": "EXIST2024",
    "id": "110967",
    "value": "YES"
  },
  {
    "test_case": "EXIST2024",
    "id": "110977",
    "value": "YES"
  },
  {
    "test_case": "EXIST2024",
    "id": "110978",
    "value": "YES"
  },
  {
    "test_case": "EXIST2024",
    "id": "110979",
    "value": "YES"
  },
  {
    "test_case": "EXIST2024",
    "id": "110983",
    "value": "YES"
  },
  {
    "test_case": "EXIST2024",
    "id": "110995",
    "value": "YES"
  },
  {
    "test_case": "EXIST2024",
    "id": "111005",
    "value": "YES"
  },
  {
    "test_case": "EXIST2024",
    "id": "111007",
    "value": "YES"
  },
  {
    "test_case": "EXIST2024",
    "id": "111009",
    "value": "YES"
  },
  {
    "test_case": "EXIST2024",
    "id": "111010",
    "value": "YES"
  },
  {
    "test_case": "EXIST2024",
    "id": "111012",
    "value": "YES"
  },
  {
    "test_case": "EXIST2024",
    "id": "111015",
    "value": "YES"
  },
  {
    "test_case": "EXIST2024",
    "id": "111016",
    "value": "YES"
  },
  {
    "test_case": "EXIST2024",
    "id": "111021",
    "value": "YES"
  },
  {
    "test_case": "EXIST2024",
    "id": "111031",
    "value": "YES"
  },
  {
    "test_case": "EXIST2024",
    "id": "111045",
    "value": "YES"
  },
  {
    "test_case": "EXIST2024",
    "id": "111048",
    "value": "YES"
  },
  {
    "test_case": "EXIST2024",
    "id": "111056",
    "value": "YES"
  },
  {
    "test_case": "EXIST2024",
    "id": "111059",
    "value": "YES"
  },
  {
    "test_case": "EXIST2024",
    "id": "111060",
    "value": "YES"
  },
  {
    "test_case": "EXIST2024",
    "id": "111072",
    "value": "YES"
  },
  {
    "test_case": "EXIST2024",
    "id": "111077",
    "value": "YES"
  },
  {
    "test_case": "EXIST2024",
    "id": "111080",
    "value": "YES"
  },
  {
    "test_case": "EXIST2024",
    "id": "111086",
    "value": "YES"
  },
  {
    "test_case": "EXIST2024",
    "id": "111087",
    "value": "YES"
  },
  {
    "test_case": "EXIST2024",
    "id": "111088",
    "value": "YES"
  },
  {
    "test_case": "EXIST2024",
    "id": "111096",
    "value": "YES"
  },
  {
    "test_case": "EXIST2024",
    "id": "111104",
    "value": "YES"
  },
  {
    "test_case": "EXIST2024",
    "id": "111106",
    "value": "YES"
  },
  {
    "test_case": "EXIST2024",
    "id": "111115",
    "value": "YES"
  },
  {
    "test_case": "EXIST2024",
    "id": "111117",
    "value": "YES"
  },
  {
    "test_case": "EXIST2024",
    "id": "111121",
    "value": "YES"
  },
  {
    "test_case": "EXIST2024",
    "id": "111122",
    "value": "YES"
  },
  {
    "test_case": "EXIST2024",
    "id": "111125",
    "value": "NO"
  },
  {
    "test_case": "EXIST2024",
    "id": "111126",
    "value": "YES"
  },
  {
    "test_case": "EXIST2024",
    "id": "111129",
    "value": "YES"
  },
  {
    "test_case": "EXIST2024",
    "id": "111141",
    "value": "YES"
  },
  {
    "test_case": "EXIST2024",
    "id": "111148",
    "value": "YES"
  },
  {
    "test_case": "EXIST2024",
    "id": "111149",
    "value": "YES"
  },
  {
    "test_case": "EXIST2024",
    "id": "111152",
    "value": "YES"
  },
  {
    "test_case": "EXIST2024",
    "id": "111163",
    "value": "YES"
  },
  {
    "test_case": "EXIST2024",
    "id": "111165",
    "value": "YES"
  },
  {
    "test_case": "EXIST2024",
    "id": "111171",
    "value": "YES"
  },
  {
    "test_case": "EXIST2024",
    "id": "111174",
    "value": "YES"
  },
  {
    "test_case": "EXIST2024",
    "id": "111177",
    "value": "YES"
  },
  {
    "test_case": "EXIST2024",
    "id": "111196",
    "value": "YES"
  },
  {
    "test_case": "EXIST2024",
    "id": "111198",
    "value": "YES"
  },
  {
    "test_case": "EXIST2024",
    "id": "111207",
    "value": "YES"
  },
  {
    "test_case": "EXIST2024",
    "id": "111216",
    "value": "YES"
  },
  {
    "test_case": "EXIST2024",
    "id": "111233",
    "value": "YES"
  },
  {
    "test_case": "EXIST2024",
    "id": "111236",
    "value": "YES"
  },
  {
    "test_case": "EXIST2024",
    "id": "111242",
    "value": "YES"
  },
  {
    "test_case": "EXIST2024",
    "id": "111248",
    "value": "YES"
  },
  {
    "test_case": "EXIST2024",
    "id": "111255",
    "value": "YES"
  },
  {
    "test_case": "EXIST2024",
    "id": "111257",
    "value": "NO"
  },
  {
    "test_case": "EXIST2024",
    "id": "111262",
    "value": "YES"
  },
  {
    "test_case": "EXIST2024",
    "id": "111264",
    "value": "YES"
  },
  {
    "test_case": "EXIST2024",
    "id": "111266",
    "value": "YES"
  },
  {
    "test_case": "EXIST2024",
    "id": "111286",
    "value": "YES"
  },
  {
    "test_case": "EXIST2024",
    "id": "111287",
    "value": "YES"
  },
  {
    "test_case": "EXIST2024",
    "id": "111288",
    "value": "YES"
  },
  {
    "test_case": "EXIST2024",
    "id": "111291",
    "value": "YES"
  },
  {
    "test_case": "EXIST2024",
    "id": "111295",
    "value": "YES"
  },
  {
    "test_case": "EXIST2024",
    "id": "111303",
    "value": "YES"
  },
  {
    "test_case": "EXIST2024",
    "id": "111305",
    "value": "YES"
  },
  {
    "test_case": "EXIST2024",
    "id": "111311",
    "value": "YES"
  },
  {
    "test_case": "EXIST2024",
    "id": "111316",
    "value": "YES"
  },
  {
    "test_case": "EXIST2024",
    "id": "111317",
    "value": "YES"
  },
  {
    "test_case": "EXIST2024",
    "id": "111318",
    "value": "YES"
  },
  {
    "test_case": "EXIST2024",
    "id": "111320",
    "value": "YES"
  },
  {
    "test_case": "EXIST2024",
    "id": "111323",
    "value": "YES"
  },
  {
    "test_case": "EXIST2024",
    "id": "111333",
    "value": "YES"
  },
  {
    "test_case": "EXIST2024",
    "id": "111335",
    "value": "YES"
  },
  {
    "test_case": "EXIST2024",
    "id": "111336",
    "value": "YES"
  },
  {
    "test_case": "EXIST2024",
    "id": "111340",
    "value": "YES"
  },
  {
    "test_case": "EXIST2024",
    "id": "111346",
    "value": "YES"
  },
  {
    "test_case": "EXIST2024",
    "id": "111350",
    "value": "YES"
  },
  {
    "test_case": "EXIST2024",
    "id": "111367",
    "value": "YES"
  },
  {
    "test_case": "EXIST2024",
    "id": "111370",
    "value": "YES"
  },
  {
    "test_case": "EXIST2024",
    "id": "111381",
    "value": "YES"
  },
  {
    "test_case": "EXIST2024",
    "id": "111383",
    "value": "YES"
  },
  {
    "test_case": "EXIST2024",
    "id": "111384",
    "value": "YES"
  },
  {
    "test_case": "EXIST2024",
    "id": "111387",
    "value": "YES"
  },
  {
    "test_case": "EXIST2024",
    "id": "111399",
    "value": "YES"
  },
  {
    "test_case": "EXIST2024",
    "id": "111412",
    "value": "YES"
  },
  {
    "test_case": "EXIST2024",
    "id": "111413",
    "value": "YES"
  },
  {
    "test_case": "EXIST2024",
    "id": "111414",
    "value": "YES"
  },
  {
    "test_case": "EXIST2024",
    "id": "111419",
    "value": "YES"
  },
  {
    "test_case": "EXIST2024",
    "id": "111425",
    "value": "NO"
  },
  {
    "test_case": "EXIST2024",
    "id": "111431",
    "value": "YES"
  },
  {
    "test_case": "EXIST2024",
    "id": "111432",
    "value": "YES"
  },
  {
    "test_case": "EXIST2024",
    "id": "111434",
    "value": "YES"
  },
  {
    "test_case": "EXIST2024",
    "id": "111435",
    "value": "YES"
  },
  {
    "test_case": "EXIST2024",
    "id": "111439",
    "value": "YES"
  },
  {
    "test_case": "EXIST2024",
    "id": "111442",
    "value": "YES"
  },
  {
    "test_case": "EXIST2024",
    "id": "111443",
    "value": "YES"
  },
  {
    "test_case": "EXIST2024",
    "id": "111445",
    "value": "YES"
  },
  {
    "test_case": "EXIST2024",
    "id": "111447",
    "value": "YES"
  },
  {
    "test_case": "EXIST2024",
    "id": "111453",
    "value": "YES"
  },
  {
    "test_case": "EXIST2024",
    "id": "111460",
    "value": "YES"
  },
  {
    "test_case": "EXIST2024",
    "id": "111479",
    "value": "YES"
  },
  {
    "test_case": "EXIST2024",
    "id": "111481",
    "value": "YES"
  },
  {
    "test_case": "EXIST2024",
    "id": "111485",
    "value": "YES"
  },
  {
    "test_case": "EXIST2024",
    "id": "111486",
    "value": "YES"
  },
  {
    "test_case": "EXIST2024",
    "id": "111495",
    "value": "YES"
  },
  {
    "test_case": "EXIST2024",
    "id": "111497",
    "value": "YES"
  },
  {
    "test_case": "EXIST2024",
    "id": "111530",
    "value": "YES"
  },
  {
    "test_case": "EXIST2024",
    "id": "111533",
    "value": "YES"
  },
  {
    "test_case": "EXIST2024",
    "id": "111543",
    "value": "YES"
  },
  {
    "test_case": "EXIST2024",
    "id": "111545",
    "value": "YES"
  },
  {
    "test_case": "EXIST2024",
    "id": "111547",
    "value": "YES"
  },
  {
    "test_case": "EXIST2024",
    "id": "111560",
    "value": "YES"
  },
  {
    "test_case": "EXIST2024",
    "id": "111569",
    "value": "YES"
  },
  {
    "test_case": "EXIST2024",
    "id": "111578",
    "value": "YES"
  },
  {
    "test_case": "EXIST2024",
    "id": "111580",
    "value": "YES"
  },
  {
    "test_case": "EXIST2024",
    "id": "111585",
    "value": "YES"
  },
  {
    "test_case": "EXIST2024",
    "id": "111592",
    "value": "YES"
  },
  {
    "test_case": "EXIST2024",
    "id": "111597",
    "value": "YES"
  },
  {
    "test_case": "EXIST2024",
    "id": "111604",
    "value": "YES"
  },
  {
    "test_case": "EXIST2024",
    "id": "111605",
    "value": "NO"
  },
  {
    "test_case": "EXIST2024",
    "id": "111608",
    "value": "NO"
  },
  {
    "test_case": "EXIST2024",
    "id": "111613",
    "value": "YES"
  },
  {
    "test_case": "EXIST2024",
    "id": "111616",
    "value": "NO"
  },
  {
    "test_case": "EXIST2024",
    "id": "111622",
    "value": "YES"
  },
  {
    "test_case": "EXIST2024",
    "id": "111624",
    "value": "YES"
  },
  {
    "test_case": "EXIST2024",
    "id": "111625",
    "value": "YES"
  },
  {
    "test_case": "EXIST2024",
    "id": "111634",
    "value": "YES"
  },
  {
    "test_case": "EXIST2024",
    "id": "111637",
    "value": "YES"
  },
  {
    "test_case": "EXIST2024",
    "id": "111639",
    "value": "YES"
  },
  {
    "test_case": "EXIST2024",
    "id": "111642",
    "value": "YES"
  },
  {
    "test_case": "EXIST2024",
    "id": "111664",
    "value": "YES"
  },
  {
    "test_case": "EXIST2024",
    "id": "111669",
    "value": "YES"
  },
  {
    "test_case": "EXIST2024",
    "id": "111677",
    "value": "YES"
  },
  {
    "test_case": "EXIST2024",
    "id": "111680",
    "value": "YES"
  },
  {
    "test_case": "EXIST2024",
    "id": "111681",
    "value": "YES"
  },
  {
    "test_case": "EXIST2024",
    "id": "111682",
    "value": "YES"
  },
  {
    "test_case": "EXIST2024",
    "id": "111689",
    "value": "YES"
  },
  {
    "test_case": "EXIST2024",
    "id": "111692",
    "value": "NO"
  },
  {
    "test_case": "EXIST2024",
    "id": "111694",
    "value": "YES"
  },
  {
    "test_case": "EXIST2024",
    "id": "111700",
    "value": "YES"
  },
  {
    "test_case": "EXIST2024",
    "id": "111705",
    "value": "YES"
  },
  {
    "test_case": "EXIST2024",
    "id": "111709",
    "value": "YES"
  },
  {
    "test_case": "EXIST2024",
    "id": "111711",
    "value": "YES"
  },
  {
    "test_case": "EXIST2024",
    "id": "111714",
    "value": "YES"
  },
  {
    "test_case": "EXIST2024",
    "id": "111722",
    "value": "YES"
  },
  {
    "test_case": "EXIST2024",
    "id": "111726",
    "value": "YES"
  },
  {
    "test_case": "EXIST2024",
    "id": "111738",
    "value": "YES"
  },
  {
    "test_case": "EXIST2024",
    "id": "111739",
    "value": "YES"
  },
  {
    "test_case": "EXIST2024",
    "id": "111741",
    "value": "YES"
  },
  {
    "test_case": "EXIST2024",
    "id": "111750",
    "value": "YES"
  },
  {
    "test_case": "EXIST2024",
    "id": "111751",
    "value": "YES"
  },
  {
    "test_case": "EXIST2024",
    "id": "111752",
    "value": "YES"
  },
  {
    "test_case": "EXIST2024",
    "id": "111753",
    "value": "NO"
  },
  {
    "test_case": "EXIST2024",
    "id": "111758",
    "value": "YES"
  },
  {
    "test_case": "EXIST2024",
    "id": "111760",
    "value": "YES"
  },
  {
    "test_case": "EXIST2024",
    "id": "111769",
    "value": "YES"
  },
  {
    "test_case": "EXIST2024",
    "id": "111775",
    "value": "YES"
  },
  {
    "test_case": "EXIST2024",
    "id": "111782",
    "value": "YES"
  },
  {
    "test_case": "EXIST2024",
    "id": "111785",
    "value": "YES"
  },
  {
    "test_case": "EXIST2024",
    "id": "111787",
    "value": "YES"
  },
  {
    "test_case": "EXIST2024",
    "id": "111791",
    "value": "YES"
  },
  {
    "test_case": "EXIST2024",
    "id": "111794",
    "value": "YES"
  },
  {
    "test_case": "EXIST2024",
    "id": "111802",
    "value": "YES"
  },
  {
    "test_case": "EXIST2024",
    "id": "111803",
    "value": "YES"
  },
  {
    "test_case": "EXIST2024",
    "id": "111806",
    "value": "YES"
  },
  {
    "test_case": "EXIST2024",
    "id": "111807",
    "value": "YES"
  },
  {
    "test_case": "EXIST2024",
    "id": "111811",
    "value": "YES"
  },
  {
    "test_case": "EXIST2024",
    "id": "111815",
    "value": "YES"
  },
  {
    "test_case": "EXIST2024",
    "id": "111816",
    "value": "YES"
  },
  {
    "test_case": "EXIST2024",
    "id": "111819",
    "value": "YES"
  },
  {
    "test_case": "EXIST2024",
    "id": "111837",
    "value": "YES"
  },
  {
    "test_case": "EXIST2024",
    "id": "111838",
    "value": "YES"
  },
  {
    "test_case": "EXIST2024",
    "id": "111844",
    "value": "YES"
  },
  {
    "test_case": "EXIST2024",
    "id": "111859",
    "value": "NO"
  },
  {
    "test_case": "EXIST2024",
    "id": "111866",
    "value": "YES"
  },
  {
    "test_case": "EXIST2024",
    "id": "111867",
    "value": "YES"
  },
  {
    "test_case": "EXIST2024",
    "id": "111868",
    "value": "YES"
  },
  {
    "test_case": "EXIST2024",
    "id": "111869",
    "value": "NO"
  },
  {
    "test_case": "EXIST2024",
    "id": "111873",
    "value": "YES"
  },
  {
    "test_case": "EXIST2024",
    "id": "111875",
    "value": "YES"
  },
  {
    "test_case": "EXIST2024",
    "id": "111881",
    "value": "YES"
  },
  {
    "test_case": "EXIST2024",
    "id": "111882",
    "value": "YES"
  },
  {
    "test_case": "EXIST2024",
    "id": "111884",
    "value": "YES"
  },
  {
    "test_case": "EXIST2024",
    "id": "111887",
    "value": "YES"
  },
  {
    "test_case": "EXIST2024",
    "id": "111888",
    "value": "YES"
  },
  {
    "test_case": "EXIST2024",
    "id": "111895",
    "value": "YES"
  },
  {
    "test_case": "EXIST2024",
    "id": "111896",
    "value": "YES"
  },
  {
    "test_case": "EXIST2024",
    "id": "111899",
    "value": "YES"
  },
  {
    "test_case": "EXIST2024",
    "id": "111906",
    "value": "YES"
  },
  {
    "test_case": "EXIST2024",
    "id": "111912",
    "value": "YES"
  },
  {
    "test_case": "EXIST2024",
    "id": "111926",
    "value": "NO"
  },
  {
    "test_case": "EXIST2024",
    "id": "111938",
    "value": "NO"
  },
  {
    "test_case": "EXIST2024",
    "id": "111944",
    "value": "NO"
  },
  {
    "test_case": "EXIST2024",
    "id": "111948",
    "value": "YES"
  },
  {
    "test_case": "EXIST2024",
    "id": "111956",
    "value": "YES"
  },
  {
    "test_case": "EXIST2024",
    "id": "111959",
    "value": "YES"
  },
  {
    "test_case": "EXIST2024",
    "id": "111962",
    "value": "YES"
  },
  {
    "test_case": "EXIST2024",
    "id": "111964",
    "value": "YES"
  },
  {
    "test_case": "EXIST2024",
    "id": "111965",
    "value": "YES"
  },
  {
    "test_case": "EXIST2024",
    "id": "111971",
    "value": "YES"
  },
  {
    "test_case": "EXIST2024",
    "id": "111982",
    "value": "YES"
  },
  {
    "test_case": "EXIST2024",
    "id": "111985",
    "value": "YES"
  },
  {
    "test_case": "EXIST2024",
    "id": "111987",
    "value": "YES"
  },
  {
    "test_case": "EXIST2024",
    "id": "111990",
    "value": "YES"
  },
  {
    "test_case": "EXIST2024",
    "id": "111992",
    "value": "YES"
  },
  {
    "test_case": "EXIST2024",
    "id": "111993",
    "value": "YES"
  },
  {
    "test_case": "EXIST2024",
    "id": "111995",
    "value": "YES"
  },
  {
    "test_case": "EXIST2024",
    "id": "112001",
    "value": "YES"
  },
  {
    "test_case": "EXIST2024",
    "id": "112003",
    "value": "YES"
  },
  {
    "test_case": "EXIST2024",
    "id": "112006",
    "value": "YES"
  },
  {
    "test_case": "EXIST2024",
    "id": "112016",
    "value": "YES"
  },
  {
    "test_case": "EXIST2024",
    "id": "112020",
    "value": "YES"
  },
  {
    "test_case": "EXIST2024",
    "id": "112027",
    "value": "YES"
  },
  {
    "test_case": "EXIST2024",
    "id": "112029",
    "value": "YES"
  },
  {
    "test_case": "EXIST2024",
    "id": "210003",
    "value": "NO"
  },
  {
    "test_case": "EXIST2024",
    "id": "210009",
    "value": "YES"
  },
  {
    "test_case": "EXIST2024",
    "id": "210015",
    "value": "YES"
  },
  {
    "test_case": "EXIST2024",
    "id": "210025",
    "value": "YES"
  },
  {
    "test_case": "EXIST2024",
    "id": "210026",
    "value": "YES"
  },
  {
    "test_case": "EXIST2024",
    "id": "210027",
    "value": "YES"
  },
  {
    "test_case": "EXIST2024",
    "id": "210034",
    "value": "YES"
  },
  {
    "test_case": "EXIST2024",
    "id": "210037",
    "value": "YES"
  },
  {
    "test_case": "EXIST2024",
    "id": "210038",
    "value": "YES"
  },
  {
    "test_case": "EXIST2024",
    "id": "210040",
    "value": "YES"
  },
  {
    "test_case": "EXIST2024",
    "id": "210043",
    "value": "YES"
  },
  {
    "test_case": "EXIST2024",
    "id": "210044",
    "value": "YES"
  },
  {
    "test_case": "EXIST2024",
    "id": "210050",
    "value": "NO"
  },
  {
    "test_case": "EXIST2024",
    "id": "210056",
    "value": "NO"
  },
  {
    "test_case": "EXIST2024",
    "id": "210069",
    "value": "NO"
  },
  {
    "test_case": "EXIST2024",
    "id": "210072",
    "value": "NO"
  },
  {
    "test_case": "EXIST2024",
    "id": "210075",
    "value": "NO"
  },
  {
    "test_case": "EXIST2024",
    "id": "210077",
    "value": "YES"
  },
  {
    "test_case": "EXIST2024",
    "id": "210082",
    "value": "NO"
  },
  {
    "test_case": "EXIST2024",
    "id": "210084",
    "value": "NO"
  },
  {
    "test_case": "EXIST2024",
    "id": "210092",
    "value": "NO"
  },
  {
    "test_case": "EXIST2024",
    "id": "210102",
    "value": "NO"
  },
  {
    "test_case": "EXIST2024",
    "id": "210105",
    "value": "YES"
  },
  {
    "test_case": "EXIST2024",
    "id": "210119",
    "value": "NO"
  },
  {
    "test_case": "EXIST2024",
    "id": "210121",
    "value": "YES"
  },
  {
    "test_case": "EXIST2024",
    "id": "210126",
    "value": "YES"
  },
  {
    "test_case": "EXIST2024",
    "id": "210131",
    "value": "NO"
  },
  {
    "test_case": "EXIST2024",
    "id": "210132",
    "value": "YES"
  },
  {
    "test_case": "EXIST2024",
    "id": "210147",
    "value": "YES"
  },
  {
    "test_case": "EXIST2024",
    "id": "210151",
    "value": "YES"
  },
  {
    "test_case": "EXIST2024",
    "id": "210165",
    "value": "YES"
  },
  {
    "test_case": "EXIST2024",
    "id": "210170",
    "value": "YES"
  },
  {
    "test_case": "EXIST2024",
    "id": "210171",
    "value": "YES"
  },
  {
    "test_case": "EXIST2024",
    "id": "210173",
    "value": "YES"
  },
  {
    "test_case": "EXIST2024",
    "id": "210175",
    "value": "YES"
  },
  {
    "test_case": "EXIST2024",
    "id": "210183",
    "value": "YES"
  },
  {
    "test_case": "EXIST2024",
    "id": "210186",
    "value": "YES"
  },
  {
    "test_case": "EXIST2024",
    "id": "210188",
    "value": "NO"
  },
  {
    "test_case": "EXIST2024",
    "id": "210194",
    "value": "YES"
  },
  {
    "test_case": "EXIST2024",
    "id": "210195",
    "value": "NO"
  },
  {
    "test_case": "EXIST2024",
    "id": "210196",
    "value": "YES"
  },
  {
    "test_case": "EXIST2024",
    "id": "210200",
    "value": "YES"
  },
  {
    "test_case": "EXIST2024",
    "id": "210208",
    "value": "YES"
  },
  {
    "test_case": "EXIST2024",
    "id": "210212",
    "value": "YES"
  },
  {
    "test_case": "EXIST2024",
    "id": "210213",
    "value": "YES"
  },
  {
    "test_case": "EXIST2024",
    "id": "210216",
    "value": "YES"
  },
  {
    "test_case": "EXIST2024",
    "id": "210220",
    "value": "NO"
  },
  {
    "test_case": "EXIST2024",
    "id": "210244",
    "value": "YES"
  },
  {
    "test_case": "EXIST2024",
    "id": "210245",
    "value": "NO"
  },
  {
    "test_case": "EXIST2024",
    "id": "210247",
    "value": "YES"
  },
  {
    "test_case": "EXIST2024",
    "id": "210249",
    "value": "YES"
  },
  {
    "test_case": "EXIST2024",
    "id": "210252",
    "value": "YES"
  },
  {
    "test_case": "EXIST2024",
    "id": "210254",
    "value": "YES"
  },
  {
    "test_case": "EXIST2024",
    "id": "210263",
    "value": "YES"
  },
  {
    "test_case": "EXIST2024",
    "id": "210266",
    "value": "NO"
  },
  {
    "test_case": "EXIST2024",
    "id": "210270",
    "value": "YES"
  },
  {
    "test_case": "EXIST2024",
    "id": "210276",
    "value": "NO"
  },
  {
    "test_case": "EXIST2024",
    "id": "210281",
    "value": "NO"
  },
  {
    "test_case": "EXIST2024",
    "id": "210282",
    "value": "YES"
  },
  {
    "test_case": "EXIST2024",
    "id": "210289",
    "value": "YES"
  },
  {
    "test_case": "EXIST2024",
    "id": "210299",
    "value": "NO"
  },
  {
    "test_case": "EXIST2024",
    "id": "210300",
    "value": "NO"
  },
  {
    "test_case": "EXIST2024",
    "id": "210314",
    "value": "YES"
  },
  {
    "test_case": "EXIST2024",
    "id": "210320",
    "value": "YES"
  },
  {
    "test_case": "EXIST2024",
    "id": "210323",
    "value": "YES"
  },
  {
    "test_case": "EXIST2024",
    "id": "210325",
    "value": "YES"
  },
  {
    "test_case": "EXIST2024",
    "id": "210326",
    "value": "YES"
  },
  {
    "test_case": "EXIST2024",
    "id": "210327",
    "value": "NO"
  },
  {
    "test_case": "EXIST2024",
    "id": "210330",
    "value": "YES"
  },
  {
    "test_case": "EXIST2024",
    "id": "210338",
    "value": "NO"
  },
  {
    "test_case": "EXIST2024",
    "id": "210339",
    "value": "NO"
  },
  {
    "test_case": "EXIST2024",
    "id": "210352",
    "value": "YES"
  },
  {
    "test_case": "EXIST2024",
    "id": "210358",
    "value": "NO"
  },
  {
    "test_case": "EXIST2024",
    "id": "210368",
    "value": "NO"
  },
  {
    "test_case": "EXIST2024",
    "id": "210374",
    "value": "YES"
  },
  {
    "test_case": "EXIST2024",
    "id": "210390",
    "value": "YES"
  },
  {
    "test_case": "EXIST2024",
    "id": "210403",
    "value": "NO"
  },
  {
    "test_case": "EXIST2024",
    "id": "210405",
    "value": "YES"
  },
  {
    "test_case": "EXIST2024",
    "id": "210407",
    "value": "NO"
  },
  {
    "test_case": "EXIST2024",
    "id": "210410",
    "value": "YES"
  },
  {
    "test_case": "EXIST2024",
    "id": "210423",
    "value": "YES"
  },
  {
    "test_case": "EXIST2024",
    "id": "210434",
    "value": "YES"
  },
  {
    "test_case": "EXIST2024",
    "id": "210446",
    "value": "YES"
  },
  {
    "test_case": "EXIST2024",
    "id": "210453",
    "value": "YES"
  },
  {
    "test_case": "EXIST2024",
    "id": "210461",
    "value": "YES"
  },
  {
    "test_case": "EXIST2024",
    "id": "210479",
    "value": "YES"
  },
  {
    "test_case": "EXIST2024",
    "id": "210483",
    "value": "YES"
  },
  {
    "test_case": "EXIST2024",
    "id": "210495",
    "value": "YES"
  },
  {
    "test_case": "EXIST2024",
    "id": "210497",
    "value": "YES"
  },
  {
    "test_case": "EXIST2024",
    "id": "210508",
    "value": "YES"
  },
  {
    "test_case": "EXIST2024",
    "id": "210510",
    "value": "YES"
  },
  {
    "test_case": "EXIST2024",
    "id": "210511",
    "value": "YES"
  },
  {
    "test_case": "EXIST2024",
    "id": "210522",
    "value": "YES"
  },
  {
    "test_case": "EXIST2024",
    "id": "210523",
    "value": "YES"
  },
  {
    "test_case": "EXIST2024",
    "id": "210527",
    "value": "YES"
  },
  {
    "test_case": "EXIST2024",
    "id": "210531",
    "value": "YES"
  },
  {
    "test_case": "EXIST2024",
    "id": "210533",
    "value": "YES"
  },
  {
    "test_case": "EXIST2024",
    "id": "210538",
    "value": "YES"
  },
  {
    "test_case": "EXIST2024",
    "id": "210542",
    "value": "YES"
  },
  {
    "test_case": "EXIST2024",
    "id": "210544",
    "value": "YES"
  },
  {
    "test_case": "EXIST2024",
    "id": "210547",
    "value": "YES"
  },
  {
    "test_case": "EXIST2024",
    "id": "210551",
    "value": "YES"
  },
  {
    "test_case": "EXIST2024",
    "id": "210554",
    "value": "YES"
  },
  {
    "test_case": "EXIST2024",
    "id": "210557",
    "value": "YES"
  },
  {
    "test_case": "EXIST2024",
    "id": "210558",
    "value": "YES"
  },
  {
    "test_case": "EXIST2024",
    "id": "210575",
    "value": "NO"
  },
  {
    "test_case": "EXIST2024",
    "id": "210581",
    "value": "YES"
  },
  {
    "test_case": "EXIST2024",
    "id": "210586",
    "value": "YES"
  },
  {
    "test_case": "EXIST2024",
    "id": "210590",
    "value": "YES"
  },
  {
    "test_case": "EXIST2024",
    "id": "210593",
    "value": "YES"
  },
  {
    "test_case": "EXIST2024",
    "id": "210599",
    "value": "YES"
  },
  {
    "test_case": "EXIST2024",
    "id": "210610",
    "value": "NO"
  },
  {
    "test_case": "EXIST2024",
    "id": "210620",
    "value": "NO"
  },
  {
    "test_case": "EXIST2024",
    "id": "210621",
    "value": "YES"
  },
  {
    "test_case": "EXIST2024",
    "id": "210623",
    "value": "YES"
  },
  {
    "test_case": "EXIST2024",
    "id": "210626",
    "value": "YES"
  },
  {
    "test_case": "EXIST2024",
    "id": "210628",
    "value": "YES"
  },
  {
    "test_case": "EXIST2024",
    "id": "210633",
    "value": "NO"
  },
  {
    "test_case": "EXIST2024",
    "id": "210637",
    "value": "NO"
  },
  {
    "test_case": "EXIST2024",
    "id": "210645",
    "value": "YES"
  },
  {
    "test_case": "EXIST2024",
    "id": "210646",
    "value": "YES"
  },
  {
    "test_case": "EXIST2024",
    "id": "210654",
    "value": "YES"
  },
  {
    "test_case": "EXIST2024",
    "id": "210664",
    "value": "YES"
  },
  {
    "test_case": "EXIST2024",
    "id": "210665",
    "value": "YES"
  },
  {
    "test_case": "EXIST2024",
    "id": "210677",
    "value": "YES"
  },
  {
    "test_case": "EXIST2024",
    "id": "210679",
    "value": "YES"
  },
  {
    "test_case": "EXIST2024",
    "id": "210680",
    "value": "NO"
  },
  {
    "test_case": "EXIST2024",
    "id": "210683",
    "value": "YES"
  },
  {
    "test_case": "EXIST2024",
    "id": "210684",
    "value": "YES"
  },
  {
    "test_case": "EXIST2024",
    "id": "210685",
    "value": "YES"
  },
  {
    "test_case": "EXIST2024",
    "id": "210686",
    "value": "NO"
  },
  {
    "test_case": "EXIST2024",
    "id": "210687",
    "value": "YES"
  },
  {
    "test_case": "EXIST2024",
    "id": "210697",
    "value": "NO"
  },
  {
    "test_case": "EXIST2024",
    "id": "210698",
    "value": "YES"
  },
  {
    "test_case": "EXIST2024",
    "id": "210701",
    "value": "YES"
  },
  {
    "test_case": "EXIST2024",
    "id": "210703",
    "value": "NO"
  },
  {
    "test_case": "EXIST2024",
    "id": "210714",
    "value": "YES"
  },
  {
    "test_case": "EXIST2024",
    "id": "210717",
    "value": "NO"
  },
  {
    "test_case": "EXIST2024",
    "id": "210721",
    "value": "NO"
  },
  {
    "test_case": "EXIST2024",
    "id": "210728",
    "value": "YES"
  },
  {
    "test_case": "EXIST2024",
    "id": "210730",
    "value": "YES"
  },
  {
    "test_case": "EXIST2024",
    "id": "210735",
    "value": "YES"
  },
  {
    "test_case": "EXIST2024",
    "id": "210744",
    "value": "YES"
  },
  {
    "test_case": "EXIST2024",
    "id": "210748",
    "value": "YES"
  },
  {
    "test_case": "EXIST2024",
    "id": "210758",
    "value": "YES"
  },
  {
    "test_case": "EXIST2024",
    "id": "210766",
    "value": "NO"
  },
  {
    "test_case": "EXIST2024",
    "id": "210770",
    "value": "NO"
  },
  {
    "test_case": "EXIST2024",
    "id": "210774",
    "value": "NO"
  },
  {
    "test_case": "EXIST2024",
    "id": "210775",
    "value": "YES"
  },
  {
    "test_case": "EXIST2024",
    "id": "210777",
    "value": "NO"
  },
  {
    "test_case": "EXIST2024",
    "id": "210780",
    "value": "NO"
  },
  {
    "test_case": "EXIST2024",
    "id": "210781",
    "value": "NO"
  },
  {
    "test_case": "EXIST2024",
    "id": "210787",
    "value": "NO"
  },
  {
    "test_case": "EXIST2024",
    "id": "210789",
    "value": "YES"
  },
  {
    "test_case": "EXIST2024",
    "id": "210790",
    "value": "NO"
  },
  {
    "test_case": "EXIST2024",
    "id": "210793",
    "value": "NO"
  },
  {
    "test_case": "EXIST2024",
    "id": "210799",
    "value": "YES"
  },
  {
    "test_case": "EXIST2024",
    "id": "210808",
    "value": "YES"
  },
  {
    "test_case": "EXIST2024",
    "id": "210813",
    "value": "YES"
  },
  {
    "test_case": "EXIST2024",
    "id": "210821",
    "value": "YES"
  },
  {
    "test_case": "EXIST2024",
    "id": "210823",
    "value": "YES"
  },
  {
    "test_case": "EXIST2024",
    "id": "210825",
    "value": "YES"
  },
  {
    "test_case": "EXIST2024",
    "id": "210826",
    "value": "YES"
  },
  {
    "test_case": "EXIST2024",
    "id": "210832",
    "value": "NO"
  },
  {
    "test_case": "EXIST2024",
    "id": "210839",
    "value": "YES"
  },
  {
    "test_case": "EXIST2024",
    "id": "210841",
    "value": "NO"
  },
  {
    "test_case": "EXIST2024",
    "id": "210842",
    "value": "NO"
  },
  {
    "test_case": "EXIST2024",
    "id": "210846",
    "value": "YES"
  },
  {
    "test_case": "EXIST2024",
    "id": "210855",
    "value": "NO"
  },
  {
    "test_case": "EXIST2024",
    "id": "210856",
    "value": "NO"
  },
  {
    "test_case": "EXIST2024",
    "id": "210859",
    "value": "YES"
  },
  {
    "test_case": "EXIST2024",
    "id": "210864",
    "value": "YES"
  },
  {
    "test_case": "EXIST2024",
    "id": "210865",
    "value": "YES"
  },
  {
    "test_case": "EXIST2024",
    "id": "210866",
    "value": "YES"
  },
  {
    "test_case": "EXIST2024",
    "id": "210868",
    "value": "YES"
  },
  {
    "test_case": "EXIST2024",
    "id": "210884",
    "value": "YES"
  },
  {
    "test_case": "EXIST2024",
    "id": "210886",
    "value": "YES"
  },
  {
    "test_case": "EXIST2024",
    "id": "210887",
    "value": "NO"
  },
  {
    "test_case": "EXIST2024",
    "id": "210888",
    "value": "YES"
  },
  {
    "test_case": "EXIST2024",
    "id": "210890",
    "value": "YES"
  },
  {
    "test_case": "EXIST2024",
    "id": "210907",
    "value": "YES"
  },
  {
    "test_case": "EXIST2024",
    "id": "210921",
    "value": "YES"
  },
  {
    "test_case": "EXIST2024",
    "id": "210922",
    "value": "YES"
  },
  {
    "test_case": "EXIST2024",
    "id": "210924",
    "value": "YES"
  },
  {
    "test_case": "EXIST2024",
    "id": "210937",
    "value": "YES"
  },
  {
    "test_case": "EXIST2024",
    "id": "210939",
    "value": "NO"
  },
  {
    "test_case": "EXIST2024",
    "id": "210942",
    "value": "NO"
  },
  {
    "test_case": "EXIST2024",
    "id": "210950",
    "value": "YES"
  },
  {
    "test_case": "EXIST2024",
    "id": "210951",
    "value": "YES"
  },
  {
    "test_case": "EXIST2024",
    "id": "210953",
    "value": "NO"
  },
  {
    "test_case": "EXIST2024",
    "id": "210955",
    "value": "NO"
  },
  {
    "test_case": "EXIST2024",
    "id": "210957",
    "value": "YES"
  },
  {
    "test_case": "EXIST2024",
    "id": "210959",
    "value": "YES"
  },
  {
    "test_case": "EXIST2024",
    "id": "210960",
    "value": "YES"
  },
  {
    "test_case": "EXIST2024",
    "id": "210977",
    "value": "NO"
  },
  {
    "test_case": "EXIST2024",
    "id": "210983",
    "value": "YES"
  },
  {
    "test_case": "EXIST2024",
    "id": "210984",
    "value": "YES"
  },
  {
    "test_case": "EXIST2024",
    "id": "210986",
    "value": "YES"
  },
  {
    "test_case": "EXIST2024",
    "id": "210993",
    "value": "YES"
  },
  {
    "test_case": "EXIST2024",
    "id": "211002",
    "value": "YES"
  },
  {
    "test_case": "EXIST2024",
    "id": "211003",
    "value": "YES"
  },
  {
    "test_case": "EXIST2024",
    "id": "211005",
    "value": "YES"
  },
  {
    "test_case": "EXIST2024",
    "id": "211023",
    "value": "YES"
  },
  {
    "test_case": "EXIST2024",
    "id": "211027",
    "value": "YES"
  },
  {
    "test_case": "EXIST2024",
    "id": "211038",
    "value": "YES"
  },
  {
    "test_case": "EXIST2024",
    "id": "211039",
    "value": "YES"
  },
  {
    "test_case": "EXIST2024",
    "id": "211048",
    "value": "NO"
  },
  {
    "test_case": "EXIST2024",
    "id": "211050",
    "value": "YES"
  },
  {
    "test_case": "EXIST2024",
    "id": "211052",
    "value": "NO"
  },
  {
    "test_case": "EXIST2024",
    "id": "211057",
    "value": "YES"
  },
  {
    "test_case": "EXIST2024",
    "id": "211060",
    "value": "YES"
  },
  {
    "test_case": "EXIST2024",
    "id": "211065",
    "value": "YES"
  },
  {
    "test_case": "EXIST2024",
    "id": "211068",
    "value": "YES"
  },
  {
    "test_case": "EXIST2024",
    "id": "211073",
    "value": "YES"
  },
  {
    "test_case": "EXIST2024",
    "id": "211074",
    "value": "NO"
  },
  {
    "test_case": "EXIST2024",
    "id": "211078",
    "value": "YES"
  },
  {
    "test_case": "EXIST2024",
    "id": "211090",
    "value": "YES"
  },
  {
    "test_case": "EXIST2024",
    "id": "211093",
    "value": "YES"
  },
  {
    "test_case": "EXIST2024",
    "id": "211109",
    "value": "NO"
  },
  {
    "test_case": "EXIST2024",
    "id": "211111",
    "value": "NO"
  },
  {
    "test_case": "EXIST2024",
    "id": "211126",
    "value": "NO"
  },
  {
    "test_case": "EXIST2024",
    "id": "211131",
    "value": "YES"
  },
  {
    "test_case": "EXIST2024",
    "id": "211136",
    "value": "NO"
  },
  {
    "test_case": "EXIST2024",
    "id": "211139",
    "value": "YES"
  },
  {
    "test_case": "EXIST2024",
    "id": "211140",
    "value": "NO"
  },
  {
    "test_case": "EXIST2024",
    "id": "211142",
    "value": "NO"
  },
  {
    "test_case": "EXIST2024",
    "id": "211147",
    "value": "YES"
  },
  {
    "test_case": "EXIST2024",
    "id": "211150",
    "value": "YES"
  },
  {
    "test_case": "EXIST2024",
    "id": "211153",
    "value": "YES"
  },
  {
    "test_case": "EXIST2024",
    "id": "211155",
    "value": "YES"
  },
  {
    "test_case": "EXIST2024",
    "id": "211168",
    "value": "YES"
  },
  {
    "test_case": "EXIST2024",
    "id": "211176",
    "value": "YES"
  },
  {
    "test_case": "EXIST2024",
    "id": "211179",
    "value": "YES"
  },
  {
    "test_case": "EXIST2024",
    "id": "211188",
    "value": "YES"
  },
  {
    "test_case": "EXIST2024",
    "id": "211192",
    "value": "YES"
  },
  {
    "test_case": "EXIST2024",
    "id": "211196",
    "value": "NO"
  },
  {
    "test_case": "EXIST2024",
    "id": "211197",
    "value": "NO"
  },
  {
    "test_case": "EXIST2024",
    "id": "211201",
    "value": "YES"
  },
  {
    "test_case": "EXIST2024",
    "id": "211207",
    "value": "NO"
  },
  {
    "test_case": "EXIST2024",
    "id": "211220",
    "value": "NO"
  },
  {
    "test_case": "EXIST2024",
    "id": "211229",
    "value": "YES"
  },
  {
    "test_case": "EXIST2024",
    "id": "211233",
    "value": "NO"
  },
  {
    "test_case": "EXIST2024",
    "id": "211234",
    "value": "YES"
  },
  {
    "test_case": "EXIST2024",
    "id": "211237",
    "value": "NO"
  },
  {
    "test_case": "EXIST2024",
    "id": "211238",
    "value": "NO"
  },
  {
    "test_case": "EXIST2024",
    "id": "211245",
    "value": "NO"
  },
  {
    "test_case": "EXIST2024",
    "id": "211247",
    "value": "YES"
  },
  {
    "test_case": "EXIST2024",
    "id": "211250",
    "value": "YES"
  },
  {
    "test_case": "EXIST2024",
    "id": "211252",
    "value": "YES"
  },
  {
    "test_case": "EXIST2024",
    "id": "211255",
    "value": "YES"
  },
  {
    "test_case": "EXIST2024",
    "id": "211259",
    "value": "YES"
  },
  {
    "test_case": "EXIST2024",
    "id": "211266",
    "value": "YES"
  },
  {
    "test_case": "EXIST2024",
    "id": "211276",
    "value": "NO"
  },
  {
    "test_case": "EXIST2024",
    "id": "211286",
    "value": "YES"
  },
  {
    "test_case": "EXIST2024",
    "id": "211291",
    "value": "YES"
  },
  {
    "test_case": "EXIST2024",
    "id": "211295",
    "value": "NO"
  },
  {
    "test_case": "EXIST2024",
    "id": "211299",
    "value": "YES"
  },
  {
    "test_case": "EXIST2024",
    "id": "211302",
    "value": "YES"
  },
  {
    "test_case": "EXIST2024",
    "id": "211309",
    "value": "YES"
  },
  {
    "test_case": "EXIST2024",
    "id": "211312",
    "value": "NO"
  },
  {
    "test_case": "EXIST2024",
    "id": "211315",
    "value": "YES"
  },
  {
    "test_case": "EXIST2024",
    "id": "211324",
    "value": "YES"
  },
  {
    "test_case": "EXIST2024",
    "id": "211326",
    "value": "YES"
  },
  {
    "test_case": "EXIST2024",
    "id": "211329",
    "value": "YES"
  },
  {
    "test_case": "EXIST2024",
    "id": "211340",
    "value": "NO"
  },
  {
    "test_case": "EXIST2024",
    "id": "211354",
    "value": "NO"
  },
  {
    "test_case": "EXIST2024",
    "id": "211357",
    "value": "NO"
  },
  {
    "test_case": "EXIST2024",
    "id": "211377",
    "value": "YES"
  },
  {
    "test_case": "EXIST2024",
    "id": "211388",
    "value": "YES"
  },
  {
    "test_case": "EXIST2024",
    "id": "211391",
    "value": "YES"
  },
  {
    "test_case": "EXIST2024",
    "id": "211395",
    "value": "YES"
  },
  {
    "test_case": "EXIST2024",
    "id": "211405",
    "value": "YES"
  },
  {
    "test_case": "EXIST2024",
    "id": "211409",
    "value": "YES"
  },
  {
    "test_case": "EXIST2024",
    "id": "211412",
    "value": "YES"
  },
  {
    "test_case": "EXIST2024",
    "id": "211416",
    "value": "YES"
  },
  {
    "test_case": "EXIST2024",
    "id": "211417",
    "value": "YES"
  },
  {
    "test_case": "EXIST2024",
    "id": "211424",
    "value": "YES"
  },
  {
    "test_case": "EXIST2024",
    "id": "211426",
    "value": "YES"
  },
  {
    "test_case": "EXIST2024",
    "id": "211428",
    "value": "YES"
  },
  {
    "test_case": "EXIST2024",
    "id": "211430",
    "value": "YES"
  },
  {
    "test_case": "EXIST2024",
    "id": "211439",
    "value": "NO"
  },
  {
    "test_case": "EXIST2024",
    "id": "211441",
    "value": "YES"
  },
  {
    "test_case": "EXIST2024",
    "id": "211456",
    "value": "YES"
  },
  {
    "test_case": "EXIST2024",
    "id": "211462",
    "value": "NO"
  },
  {
    "test_case": "EXIST2024",
    "id": "211466",
    "value": "NO"
  },
  {
    "test_case": "EXIST2024",
    "id": "211473",
    "value": "NO"
  },
  {
    "test_case": "EXIST2024",
    "id": "211478",
    "value": "YES"
  },
  {
    "test_case": "EXIST2024",
    "id": "211485",
    "value": "YES"
  },
  {
    "test_case": "EXIST2024",
    "id": "211487",
    "value": "NO"
  },
  {
    "test_case": "EXIST2024",
    "id": "211492",
    "value": "YES"
  },
  {
    "test_case": "EXIST2024",
    "id": "211496",
    "value": "NO"
  },
  {
    "test_case": "EXIST2024",
    "id": "211497",
    "value": "YES"
  },
  {
    "test_case": "EXIST2024",
    "id": "211498",
    "value": "YES"
  },
  {
    "test_case": "EXIST2024",
    "id": "211500",
    "value": "NO"
  },
  {
    "test_case": "EXIST2024",
    "id": "211505",
    "value": "NO"
  },
  {
    "test_case": "EXIST2024",
    "id": "211508",
    "value": "YES"
  },
  {
    "test_case": "EXIST2024",
    "id": "211511",
    "value": "YES"
  },
  {
    "test_case": "EXIST2024",
    "id": "211514",
    "value": "YES"
  },
  {
    "test_case": "EXIST2024",
    "id": "211516",
    "value": "NO"
  },
  {
    "test_case": "EXIST2024",
    "id": "211528",
    "value": "YES"
  },
  {
    "test_case": "EXIST2024",
    "id": "211530",
    "value": "NO"
  },
  {
    "test_case": "EXIST2024",
    "id": "211531",
    "value": "NO"
  },
  {
    "test_case": "EXIST2024",
    "id": "211532",
    "value": "NO"
  },
  {
    "test_case": "EXIST2024",
    "id": "211533",
    "value": "NO"
  },
  {
    "test_case": "EXIST2024",
    "id": "211538",
    "value": "NO"
  },
  {
    "test_case": "EXIST2024",
    "id": "211546",
    "value": "YES"
  },
  {
    "test_case": "EXIST2024",
    "id": "211547",
    "value": "NO"
  },
  {
    "test_case": "EXIST2024",
    "id": "211550",
    "value": "YES"
  },
  {
    "test_case": "EXIST2024",
    "id": "211556",
    "value": "NO"
  },
  {
    "test_case": "EXIST2024",
    "id": "211570",
    "value": "YES"
  },
  {
    "test_case": "EXIST2024",
    "id": "211580",
    "value": "NO"
  },
  {
    "test_case": "EXIST2024",
    "id": "211581",
    "value": "NO"
  },
  {
    "test_case": "EXIST2024",
    "id": "211599",
    "value": "NO"
  },
  {
    "test_case": "EXIST2024",
    "id": "211603",
    "value": "YES"
  },
  {
    "test_case": "EXIST2024",
    "id": "211604",
    "value": "YES"
  },
  {
    "test_case": "EXIST2024",
    "id": "211610",
    "value": "NO"
  },
  {
    "test_case": "EXIST2024",
    "id": "211614",
    "value": "YES"
  },
  {
    "test_case": "EXIST2024",
    "id": "211619",
    "value": "NO"
  },
  {
    "test_case": "EXIST2024",
    "id": "211648",
    "value": "NO"
  },
  {
    "test_case": "EXIST2024",
    "id": "211657",
    "value": "YES"
  },
  {
    "test_case": "EXIST2024",
    "id": "211664",
    "value": "NO"
  },
  {
    "test_case": "EXIST2024",
    "id": "211669",
    "value": "NO"
  },
  {
    "test_case": "EXIST2024",
    "id": "211688",
    "value": "NO"
  },
  {
    "test_case": "EXIST2024",
    "id": "211689",
    "value": "YES"
  },
  {
    "test_case": "EXIST2024",
    "id": "211697",
    "value": "NO"
  },
  {
    "test_case": "EXIST2024",
    "id": "211711",
    "value": "NO"
  },
  {
    "test_case": "EXIST2024",
    "id": "211717",
    "value": "YES"
  },
  {
    "test_case": "EXIST2024",
    "id": "211719",
    "value": "NO"
  },
  {
    "test_case": "EXIST2024",
    "id": "211731",
    "value": "NO"
  },
  {
    "test_case": "EXIST2024",
    "id": "211735",
    "value": "YES"
  },
  {
    "test_case": "EXIST2024",
    "id": "211736",
    "value": "YES"
  },
  {
    "test_case": "EXIST2024",
    "id": "211737",
    "value": "NO"
  },
  {
    "test_case": "EXIST2024",
    "id": "211740",
    "value": "NO"
  },
  {
    "test_case": "EXIST2024",
    "id": "211742",
    "value": "YES"
  },
  {
    "test_case": "EXIST2024",
    "id": "211749",
    "value": "NO"
  },
  {
    "test_case": "EXIST2024",
    "id": "211750",
    "value": "YES"
  },
  {
    "test_case": "EXIST2024",
    "id": "211754",
    "value": "NO"
  },
  {
    "test_case": "EXIST2024",
    "id": "211755",
    "value": "YES"
  },
  {
    "test_case": "EXIST2024",
    "id": "211757",
    "value": "YES"
  },
  {
    "test_case": "EXIST2024",
    "id": "211763",
    "value": "YES"
  },
  {
    "test_case": "EXIST2024",
    "id": "211764",
    "value": "YES"
  },
  {
    "test_case": "EXIST2024",
    "id": "211768",
    "value": "NO"
  },
  {
    "test_case": "EXIST2024",
    "id": "211774",
    "value": "YES"
  },
  {
    "test_case": "EXIST2024",
    "id": "211777",
    "value": "NO"
  },
  {
    "test_case": "EXIST2024",
    "id": "211778",
    "value": "YES"
  },
  {
    "test_case": "EXIST2024",
    "id": "211783",
    "value": "YES"
  },
  {
    "test_case": "EXIST2024",
    "id": "211789",
    "value": "YES"
  },
  {
    "test_case": "EXIST2024",
    "id": "211792",
    "value": "YES"
  },
  {
    "test_case": "EXIST2024",
    "id": "211796",
    "value": "YES"
  },
  {
    "test_case": "EXIST2024",
    "id": "211798",
    "value": "YES"
  },
  {
    "test_case": "EXIST2024",
    "id": "211800",
    "value": "YES"
  },
  {
    "test_case": "EXIST2024",
    "id": "211803",
    "value": "YES"
  },
  {
    "test_case": "EXIST2024",
    "id": "211817",
    "value": "YES"
  },
  {
    "test_case": "EXIST2024",
    "id": "211818",
    "value": "YES"
  },
  {
    "test_case": "EXIST2024",
    "id": "211822",
    "value": "YES"
  },
  {
    "test_case": "EXIST2024",
    "id": "211827",
    "value": "NO"
  },
  {
    "test_case": "EXIST2024",
    "id": "211829",
    "value": "YES"
  },
  {
    "test_case": "EXIST2024",
    "id": "211831",
    "value": "YES"
  },
  {
    "test_case": "EXIST2024",
    "id": "211833",
    "value": "YES"
  },
  {
    "test_case": "EXIST2024",
    "id": "211836",
    "value": "YES"
  },
  {
    "test_case": "EXIST2024",
    "id": "211839",
    "value": "YES"
  },
  {
    "test_case": "EXIST2024",
    "id": "211842",
    "value": "YES"
  },
  {
    "test_case": "EXIST2024",
    "id": "211843",
    "value": "NO"
  },
  {
    "test_case": "EXIST2024",
    "id": "211846",
    "value": "NO"
  },
  {
    "test_case": "EXIST2024",
    "id": "211849",
    "value": "NO"
  },
  {
    "test_case": "EXIST2024",
    "id": "211850",
    "value": "NO"
  },
  {
    "test_case": "EXIST2024",
    "id": "211859",
    "value": "YES"
  },
  {
    "test_case": "EXIST2024",
    "id": "211861",
    "value": "YES"
  },
  {
    "test_case": "EXIST2024",
    "id": "211862",
    "value": "NO"
  },
  {
    "test_case": "EXIST2024",
    "id": "211863",
    "value": "YES"
  },
  {
    "test_case": "EXIST2024",
    "id": "211864",
    "value": "YES"
  },
  {
    "test_case": "EXIST2024",
    "id": "211880",
    "value": "YES"
  },
  {
    "test_case": "EXIST2024",
    "id": "211881",
    "value": "YES"
  },
  {
    "test_case": "EXIST2024",
    "id": "211886",
    "value": "YES"
  },
  {
    "test_case": "EXIST2024",
    "id": "211891",
    "value": "NO"
  },
  {
    "test_case": "EXIST2024",
    "id": "211900",
    "value": "YES"
  },
  {
    "test_case": "EXIST2024",
    "id": "211903",
    "value": "YES"
  },
  {
    "test_case": "EXIST2024",
    "id": "211914",
    "value": "YES"
  },
  {
    "test_case": "EXIST2024",
    "id": "211942",
    "value": "YES"
  },
  {
    "test_case": "EXIST2024",
    "id": "211946",
    "value": "YES"
  },
  {
    "test_case": "EXIST2024",
    "id": "211950",
    "value": "NO"
  },
  {
    "test_case": "EXIST2024",
    "id": "211952",
    "value": "NO"
  },
  {
    "test_case": "EXIST2024",
    "id": "211954",
    "value": "YES"
  },
  {
    "test_case": "EXIST2024",
    "id": "211956",
    "value": "NO"
  },
  {
    "test_case": "EXIST2024",
    "id": "211958",
    "value": "YES"
  },
  {
    "test_case": "EXIST2024",
    "id": "211961",
    "value": "YES"
  },
  {
    "test_case": "EXIST2024",
    "id": "211971",
    "value": "YES"
  },
  {
    "test_case": "EXIST2024",
    "id": "211973",
    "value": "YES"
  },
  {
    "test_case": "EXIST2024",
    "id": "211983",
    "value": "YES"
  },
  {
    "test_case": "EXIST2024",
    "id": "211985",
    "value": "YES"
  },
  {
    "test_case": "EXIST2024",
    "id": "211990",
    "value": "YES"
  },
  {
    "test_case": "EXIST2024",
    "id": "211992",
    "value": "YES"
  },
  {
    "test_case": "EXIST2024",
    "id": "211995",
    "value": "YES"
  },
  {
    "test_case": "EXIST2024",
    "id": "211997",
    "value": "YES"
  },
  {
    "test_case": "EXIST2024",
    "id": "212000",
    "value": "YES"
  }
]